cloudshell/__init__.py
cloudshell/layer_one/__init__.py
cloudshell/layer_one/core/__init__.py
cloudshell/layer_one/core/command_executor.py
cloudshell/layer_one/core/connection_handler.py
cloudshell/layer_one/core/driver_commands_interface.py
cloudshell/layer_one/core/driver_listener.py
cloudshell/layer_one/core/layer_one_driver_exception.py
cloudshell/layer_one/core/helper/__init__.py
cloudshell/layer_one/core/helper/logger.py
cloudshell/layer_one/core/helper/runtime_configuration.py
cloudshell/layer_one/core/helper/xml_helper.py
cloudshell/layer_one/core/helper/xml_logger.py
cloudshell/layer_one/core/request/__init__.py
cloudshell/layer_one/core/request/command_request.py
cloudshell/layer_one/core/request/requests_parser.py
cloudshell/layer_one/core/response/__init__.py
cloudshell/layer_one/core/response/command_response.py
cloudshell/layer_one/core/response/command_responses_builder.py
cloudshell/layer_one/core/response/response_info.py
cloudshell/layer_one/core/response/resource_info/__init__.py
cloudshell/layer_one/core/response/resource_info/resource_info_builder.py
cloudshell/layer_one/core/response/resource_info/entities/__init__.py
cloudshell/layer_one/core/response/resource_info/entities/attributes.py
cloudshell/layer_one/core/response/resource_info/entities/base.py
cloudshell/layer_one/core/response/resource_info/entities/blade.py
cloudshell/layer_one/core/response/resource_info/entities/chassis.py
cloudshell/layer_one/core/response/resource_info/entities/port.py
cloudshell/layer_one/core/response/resource_info/entities/validators.py
cloudshell/layer_one/core/response/resource_info/templates/resource_attribute_template.xml
cloudshell/layer_one/core/response/resource_info/templates/resource_incoming_map_template.xml
cloudshell/layer_one/core/response/resource_info/templates/resource_template.xml
cloudshell/layer_one/core/response/templates/command_response_template.xml
cloudshell/layer_one/core/response/templates/error_response.xml
cloudshell_l1_networking_core-2.0.1.dist-info/METADATA
cloudshell_l1_networking_core-2.0.1.dist-info/WHEEL
cloudshell_l1_networking_core-2.0.1.dist-info/entry_points.txt
cloudshell_l1_networking_core-2.0.1.dist-info/top_level.txt
cloudshell_l1_networking_core-2.0.1.dist-info/RECORD
