Metadata-Version: 2.1
Name: cloudshell-l1-networking-core
Version: 2.0.1
Summary: QualiSystems CloudShell L1 networking core package
Home-page: https://github.com/QualiSystems/cloudshell-l1-networking-core
Author: Quali
Author-email: info@quali.com
License: Apache Software License 2.0
Keywords: core cloudshell quali layer-one
Requires-Python: ~=3.7
Requires-Dist: PyYAML
